whitebox_plugin_stratux/pyproject.toml
whitebox_plugin_stratux/__init__.py
whitebox_plugin_stratux/whitebox_plugin_stratux.py
whitebox_test_plugin_stratux/__init__.py
whitebox_test_plugin_stratux/test_whitebox_plugin_stratux.py
whitebox_test_plugin_stratux/test_whitebox_plugin_stratux_integration.py
whitebox_plugin_stratux-0.1.9.dist-info/LICENSE
whitebox_plugin_stratux-0.1.9.dist-info/METADATA
whitebox_plugin_stratux-0.1.9.dist-info/WHEEL
whitebox_plugin_stratux-0.1.9.dist-info/RECORD
